threaded_mvc/__init__.py
threaded_mvc/threaded_mvc.py
threaded_mvc-0.0.4.dist-info/METADATA
threaded_mvc-0.0.4.dist-info/WHEEL
threaded_mvc-0.0.4.dist-info/top_level.txt
threaded_mvc-0.0.4.dist-info/RECORD
