Metadata-Version: 2.1
Name: threaded-mvc
Version: 0.0.4
Summary: Threaded Model View Controller classes.
Home-page: https://github.com/Galen-dp/threaded_mvc
Author: Doug Peterson
Author-email: doug@notre-chateau.com
License: BSD 3-clause
Project-URL: Documentation, https://https://threaded-mvc.readthedocs.io
Project-URL: Source, https://github.com/Galen-dp/threaded_mvc
Project-URL: Tracker, https://github.com/Galen-dp/threaded_mvc/issues
Project-URL: PyPi, https://pypi.org/project/threaded-mvc/
Keywords: threaded_mvc,mvc,model view controller
Classifier: Development Status :: 2 - Pre-Alpha
Classifier: Intended Audience :: Developers
Classifier: License :: OSI Approved :: BSD License
Classifier: Natural Language :: English
Classifier: Operating System :: MacOS
Classifier: Operating System :: Microsoft :: Windows
Classifier: Operating System :: POSIX :: Linux
Classifier: Programming Language :: Python :: 3
Classifier: Programming Language :: Python :: 3.7
Classifier: Programming Language :: Python :: 3.8
Classifier: Programming Language :: Python :: 3.9
Classifier: Programming Language :: Python :: 3.10
Classifier: Topic :: Software Development
Classifier: Topic :: Software Development :: Libraries :: Python Modules
Classifier: Topic :: Software Development :: User Interfaces
Requires-Python: >=3.7
